Eval_param_EM/Eval_param.py
Eval_param_EM/try.py
Eval_param_EM-1.0.2.dist-info/LICENSE
Eval_param_EM-1.0.2.dist-info/METADATA
Eval_param_EM-1.0.2.dist-info/WHEEL
Eval_param_EM-1.0.2.dist-info/entry_points.txt
Eval_param_EM-1.0.2.dist-info/top_level.txt
Eval_param_EM-1.0.2.dist-info/RECORD
